mcpi_world/__init__.py
mcpi_world/level_file.py
mcpi_world-1.0.1.dist-info/LICENSE
mcpi_world-1.0.1.dist-info/METADATA
mcpi_world-1.0.1.dist-info/WHEEL
mcpi_world-1.0.1.dist-info/top_level.txt
mcpi_world-1.0.1.dist-info/RECORD
