Metadata-Version: 2.1
Name: mcpi-world
Version: 1.0.1
Summary: level.dat editor for MCPE versions => 0.8.1
Home-page: UNKNOWN
Author: The StevePi Organization
Maintainer: LEHAtupointow
Maintainer-email: leha2@tuxfamily.org
License: UNKNOWN
Platform: UNKNOWN
Requires-Dist: amulet-nbt
